monetary_correction/__init__.py
monetary_correction/config.py
monetary_correction/core.py
monetary_correction/domain.py
monetary_correction/sgs.py
monetary_correction/utils.py
monetary_correction-0.1.0.dist-info/licenses/LICENSE
monetary_correction-0.1.0.dist-info/METADATA
monetary_correction-0.1.0.dist-info/WHEEL
monetary_correction-0.1.0.dist-info/top_level.txt
monetary_correction-0.1.0.dist-info/RECORD
