Metadata-Version: 2.4
Name: monetary-correction
Version: 0.1.0
Summary: A simple, robust Python library to deflate nominal Brazilian Reais using official price indexes from the Brazilian Central Bank's SGS (Sistema Gerenciador de Séries Temporais) API.
Author-email: Alexsander Lopes Camargos <alexcamargos@gmail.com>
License: MIT
Project-URL: Repository, https://github.com/alexcamargos/monetary-correction
Project-URL: Issues, https://github.com/alexcamargos/monetary-correction/issues
Keywords: finance,economics,inflation,brazil,bcb,sgs,ipca,igp-m,inpc,monetary-correction,deflation
Classifier: Development Status :: 3 - Alpha
Classifier: Intended Audience :: Developers
Classifier: Intended Audience :: Financial and Insurance Industry
Classifier: License :: OSI Approved :: MIT License
Classifier: Natural Language :: Portuguese (Brazilian)
Classifier: Operating System :: OS Independent
Classifier: Programming Language :: Python :: 3
Classifier: Programming Language :: Python :: 3.13
Classifier: Topic :: Office/Business :: Financial
Classifier: Topic :: Software Development :: Libraries :: Python Modules
Classifier: Topic :: Utilities
Requires-Python: >=3.13
License-File: LICENSE
Requires-Dist: grab-harvester>=0.0.1
Requires-Dist: polars>=0.20.0
Requires-Dist: requests>=2.31.0
Requires-Dist: typer>=0.9.0
Provides-Extra: dev
Requires-Dist: pytest>=8.0.0; extra == "dev"
Requires-Dist: pytest-mock>=3.12.0; extra == "dev"
Requires-Dist: pytest-cov>=4.1.0; extra == "dev"
Requires-Dist: pre-commit>=3.5.0; extra == "dev"
Dynamic: license-file
